README.md
setup.py
nra_project/__init__.py
nra_project/dashboard.py
nra_project.egg-info/PKG-INFO
nra_project.egg-info/SOURCES.txt
nra_project.egg-info/dependency_links.txt
nra_project.egg-info/top_level.txt